ijmfttxt/__init__.py
ijmfttxt/apds.py
ijmfttxt/clock.py
ijmfttxt/color.py
ijmfttxt/constants.py
ijmfttxt/errors.py
ijmfttxt/keyboard.py
ijmfttxt/txt.py
ijmfttxt/ftrobopy/__init__.py
ijmfttxt/ftrobopy/ftrobopy.py
ijmfttxt-1.9.9.dist-info/LICENSE
ijmfttxt-1.9.9.dist-info/METADATA
ijmfttxt-1.9.9.dist-info/WHEEL
ijmfttxt-1.9.9.dist-info/top_level.txt
ijmfttxt-1.9.9.dist-info/RECORD
