Metadata-Version: 2.1
Name: ijmfttxt
Version: 1.9.9
Summary: Erweiterung zu ftrobopy
Home-page: https://github.com/IJMTutorSES/ijmfttxt
Author: Sebastian Specht
Author-email: s.specht@ijm-online.de
License: MIT
Keywords: ftrobopy fischertechnik txt ijm
Classifier: Development Status :: 5 - Production/Stable
Classifier: Intended Audience :: Education
Classifier: License :: OSI Approved :: MIT License
Classifier: Natural Language :: English
Classifier: Programming Language :: Python :: 3.9
Classifier: Topic :: Education
License-File: LICENSE
Requires-Dist: pynput
